{
  "/_global-error/page": "app/_global-error/page.js",
  "/_not-found/page": "app/_not-found/page.js",
  "/api/provider/register/[id]/route": "app/api/provider/register/[id]/route.js",
  "/api/provider/register/route": "app/api/provider/register/route.js",
  "/favicon.ico/route": "app/favicon.ico/route.js",
  "/home/page": "app/home/page.js",
  "/login/page": "app/login/page.js",
  "/manifest.webmanifest/route": "app/manifest.webmanifest/route.js",
  "/onboarding/page": "app/onboarding/page.js",
  "/onboarding/ready/page": "app/onboarding/ready/page.js",
  "/onboarding/why-della/page": "app/onboarding/why-della/page.js",
  "/onboarding/why/page": "app/onboarding/why/page.js",
  "/page": "app/page.js",
  "/profile/addresses/page": "app/profile/addresses/page.js",
  "/profile/bookings/page": "app/profile/bookings/page.js",
  "/profile/edit/page": "app/profile/edit/page.js",
  "/profile/page": "app/profile/page.js",
  "/profile/settings/page": "app/profile/settings/page.js",
  "/provider/dashboard/[id]/page": "app/provider/dashboard/[id]/page.js",
  "/provider/dashboard/page": "app/provider/dashboard/page.js",
  "/provider/register/page": "app/provider/register/page.js",
  "/providers/page": "app/providers/page.js",
  "/register/page": "app/register/page.js",
  "/register/success/page": "app/register/success/page.js",
  "/register/verify/page": "app/register/verify/page.js",
  "/signup/page": "app/signup/page.js",
  "/signup/user/page": "app/signup/user/page.js"
}